loghive/__init__.py
loghive/alembic.ini
loghive/db.py
loghive/alembic/README
loghive/alembic/env.py
loghive/alembic/script.py.mako
loghive/alembic/versions/__init__.py
loghive/alembic/versions/abd7228d3b72_migration.py
loghive/alembic/versions/d1fa1bf0f4da_add_information_field.py
loghive/consumer/__init__.py
loghive/consumer/rabbitmqconsumer.py
loghive/logger/__init__.py
loghive/logger/rabbitmqlogger.py
loghive/main/__init__.py
loghive/main/database.py
loghive/main/models.py
loghive/main/sendemail.py
loghive/main/settings.py
loghive/main/utils.py
loghive/sample/__init__.py
loghive/sample/fastapi_application.py
loghive/sample/flask_application.py
loghive-1.0.0.dist-info/LICENSE.txt
loghive-1.0.0.dist-info/METADATA
loghive-1.0.0.dist-info/WHEEL
loghive-1.0.0.dist-info/top_level.txt
loghive-1.0.0.dist-info/RECORD
